valo_api/__init__.py
valo_api/config.py
valo_api/endpoint.py
valo_api/endpoints/__init__.py
valo_api/endpoints_config.py
valo_api/exceptions/__init__.py
valo_api/exceptions/rate_limit.py
valo_api/exceptions/valo_api_exception.py
valo_api/responses/__init__.py
valo_api/responses/account_details.py
valo_api/responses/competitive_updates_raw.py
valo_api/responses/content.py
valo_api/responses/error_response.py
valo_api/responses/leaderboard.py
valo_api/responses/lifetime_match.py
valo_api/responses/match_details_raw.py
valo_api/responses/match_history.py
valo_api/responses/match_history_raw.py
valo_api/responses/mmr_details.py
valo_api/responses/mmr_history.py
valo_api/responses/mmr_raw.py
valo_api/responses/status.py
valo_api/responses/store_featured.py
valo_api/responses/version_info.py
valo_api/responses/website.py
valo_api/utils/__init__.py
valo_api/utils/dict_struct.py
valo_api/utils/fetch_endpoint.py
valo_api-2.1.0.dist-info/LICENSE
valo_api-2.1.0.dist-info/METADATA
valo_api-2.1.0.dist-info/WHEEL
valo_api-2.1.0.dist-info/entry_points.txt
valo_api-2.1.0.dist-info/RECORD
