Metadata-Version: 2.3
Name: valo_api
Version: 2.1.0
Summary: Valorant API Wrapper for https://github.com/Henrik-3/unofficial-valorant-api
License: MIT
Author: Manuel Raimann
Author-email: raimannma@outlook.de
Requires-Python: >=3.9,<4.0
Classifier: Development Status :: 5 - Production/Stable
Classifier: Intended Audience :: Developers
Classifier: License :: OSI Approved :: MIT License
Classifier: Operating System :: OS Independent
Classifier: Programming Language :: Python :: 3
Classifier: Programming Language :: Python :: 3.9
Classifier: Programming Language :: Python :: 3.10
Classifier: Programming Language :: Python :: 3.11
Classifier: Programming Language :: Python :: 3.12
Classifier: Programming Language :: Python :: 3.13
Classifier: Programming Language :: Python :: 3.8
Classifier: Topic :: Software Development :: Libraries :: Python Modules
Provides-Extra: async
Requires-Dist: Pillow (>=11.1.0,<12.0.0)
Requires-Dist: aiohttp (>=3.11.13,<4.0.0) ; extra == "async"
Requires-Dist: asyncio[speedups] (>=3.4.3,<4.0.0) ; extra == "async"
Requires-Dist: msgspec (>=0.19.0,<0.20.0)
Requires-Dist: requests (>=2.32.3,<3.0.0)
Project-URL: Homepage, https://github.com/raimannma/ValorantAPI
Project-URL: Repository, https://github.com/raimannma/ValorantAPI
